[{"s": "dop-klaviatura-dlya-noutbuka-kak-vklyuchit", "t": "Как подключить дополнительную клавиатуру к ноутбуку — пошаговое руководство", "i": "🔌", "c": "podklyuchenie-i-nastrojka"}, {"s": "dopolnitelnaya-klaviatura-chto-eto-znachit", "t": "Дополнительная клавиатура — что это и зачем она нужна?", "i": "🔌", "c": "podklyuchenie-i-nastrojka"}, {"s": "dopolnitelnaya-klaviatura-na-noutbuke-kak-vklyuchit", "t": "Как включить дополнительную клавиатуру на ноутбуке: пошаговая инструкция", "i": "🔌", "c": "podklyuchenie-i-nastrojka"}, {"s": "dollar-kak-vyglyadit-na-klaviature", "t": "Как напечатать знак доллара ($) на клавиатуре — все способы", "i": "🔣", "c": "spetssimvoly-i-znaki"}, {"s": "dopolnitelnaya-tsifrovaya-klaviatura-peremeshchaet-kursor-kogda-num-lock-gorit", "t": "Клавиатура: курсор двигается при включенном Num Lock — причины и решения", "i": "🌐", "c": "raskladka-i-yazyki"}, {"s": "dostupnaya-virtualnaya-klaviatura-kak-ubrat-na-androide", "t": "Как убрать доступную виртуальную клавиатуру на Android: полное руководство", "i": "📱", "c": "klaviatury-na-smartfonakh"}, {"s": "dollar-kak-pishetsya-znak-na-klaviature", "t": "Как поставить знак доллара $ на клавиатуре: 5 рабочих способов", "i": "🔣", "c": "spetssimvoly-i-znaki"}, {"s": "dobavit-zvuk-na-klaviature-kompyutera-kak", "t": "Как добавить звук на клавиатуру компьютера: полное руководство для Windows и Mac", "i": "🔌", "c": "podklyuchenie-i-nastrojka"}, {"s": "dopolnitelnye-klavishi-na-klaviature-kak-nastroit", "t": "Как настроить дополнительные клавиши на клавиатуре: Полное руководство", "i": "⚡", "c": "goryachie-klavishi"}, {"s": "dopolnitelnaya-tsifrovaya-klaviatura-vvodit-bukvy-kogda-num-lock-gorit", "t": "Num Lock горит, но клавиатура вводит буквы: причины и исправление", "i": "🌐", "c": "raskladka-i-yazyki"}, {"s": "dobavit-yazyk-na-android-kak-klaviature", "t": "Как добавить язык на Android: полная настройка клавиатуры Gboard и AOSP", "i": "🌐", "c": "raskladka-i-yazyki"}, {"s": "double-shot-klaviatura-chto-eto", "t": "Double Shot клавиатура: что это, как работает и почему это лучше печати", "i": "🌈", "c": "podsvetka-i-dizajn"}, {"s": "dopolnitelnaya-tsifrovaya-klaviatura-v-bloknote-gde", "t": "Где находится дополнительная цифровая клавиатура в блокноте: 3 способа", "i": "🌐", "c": "raskladka-i-yazyki"}, {"s": "do-diez-gde-nakhoditsya-na-klaviature", "t": "Где находится диез на клавиатуре: клавиши, символы и способы ввода", "i": "🔣", "c": "spetssimvoly-i-znaki"}, {"s": "dopolnitelnaya-klaviatura-kak-vklyuchit", "t": "Как включить дополнительную клавиатуру: полные инструкции и советы", "i": "🔌", "c": "podklyuchenie-i-nastrojka"}, {"s": "don-t-starve-kak-atakovat-na-klaviature", "t": "Как атаковать в Don't Starve: управление клавиатурой и действия", "i": "🎮", "c": "igrovye-nastrojki"}, {"s": "dobavit-vtoruyu-raskladku-klaviatury-windows-10-chto-eto", "t": "Как добавить вторую раскладку клавиатуры в Windows 10: пошаговая инструкция", "i": "🌐", "c": "raskladka-i-yazyki"}, {"s": "dostupnaya-ekrannaya-klaviatura-vyskakivaet-na-telefone-kak-ubrat", "t": "Как убрать доступную экранную клавиатуру на телефоне: полное руководство", "i": "📱", "c": "klaviatury-na-smartfonakh"}, {"s": "dopolnitelnaya-tsifrovaya-klaviatura-v-bloknote-gde-nakhoditsya", "t": "Где находится дополнительная цифровая клавиатура в блокноте", "i": "🌐", "c": "raskladka-i-yazyki"}, {"s": "dollar-na-klaviature-noutbuka-kak-napisat", "t": "Как набрать знак доллара на ноутбуке: все способы и комбинации", "i": "⚡", "c": "goryachie-klavishi"}, {"s": "dopolnitelnaya-klaviatura-dlya-noutbuka-kak-vklyuchit", "t": "Как включить дополнительную клавиатуру ноутбука: полноразмерную и цифровую", "i": "🔌", "c": "podklyuchenie-i-nastrojka"}, {"s": "dop-klaviatura-na-noutbuke-kak-vklyuchit", "t": "Как включить дополнительную клавиатуру на ноутбуке: полные инструкции", "i": "⚡", "c": "goryachie-klavishi"}, {"s": "dopolnitelnaya-tsifrovaya-klaviatura-vvodit-bukvy-kogda-num-lock", "t": "Num Lock печатает буквы вместо цифр: причины и исправления", "i": "🌐", "c": "raskladka-i-yazyki"}, {"s": "dolphin-emulator-kak-nastroit-klaviaturu", "t": "Dolphin Emulator: полная настройка клавиатуры и геймпада", "i": "🎮", "c": "igrovye-nastrojki"}, {"s": "dopolnitelnaya-klaviatura-kak-otklyuchit", "t": "Как отключить дополнительную клавиатуру: Windows, Android, iOS", "i": "🌐", "c": "raskladka-i-yazyki"}, {"s": "dobavit-vtoruyu-raskladku-klaviatury-windows-10-chto-znachit", "t": "Как добавить вторую раскладку в Windows 10: полное руководство по настройке", "i": "🌐", "c": "raskladka-i-yazyki"}, {"s": "dosbox-kak-smenit-raskladku-klaviatury", "t": "Как сменить раскладку клавиатуры в DOSBox: полное руководство", "i": "🌐", "c": "raskladka-i-yazyki"}, {"s": "dopolnitelnaya-tsifrovaya-klaviatura-kak-vklyuchit", "t": "Как включить дополнительную цифровую клавиатуру: Полное руководство", "i": "🔌", "c": "podklyuchenie-i-nastrojka"}, {"s": "dobavilsya-yazyk-klaviatury-kak-ubrat", "t": "Как убрать лишний язык клавиатуры: полное руководство", "i": "🌐", "c": "raskladka-i-yazyki"}, {"s": "dok-klaviatura-chto-eto", "t": "Док клавиатура: что это, как подключить и выбрать док-станцию", "i": "🔌", "c": "podklyuchenie-i-nastrojka"}, {"s": "dobavochnaya-klaviatura-kak-otklyuchit", "t": "Как отключить добавочную клавиатуру: полные инструкции для Windows и Android", "i": "🌐", "c": "raskladka-i-yazyki"}, {"s": "doklad-klaviatura-chto-takoe", "t": "Опрос доклад клавиатура: что это, виды и диагностика неисправностей", "i": "🛠️", "c": "remont-i-ustranenie-neispravnostej"}, {"s": "doa-6-kak-igrat-na-klaviature", "t": "Как играть на клавиатуре в Dead or Alive 6: управление и настройка", "i": "🎮", "c": "igrovye-nastrojki"}, {"s": "double-injection-klaviatura-chto-eto", "t": "Double Injection клавиатура: что это, как работает и зачем нужна", "i": "🌈", "c": "podsvetka-i-dizajn"}]