[{"s": "gingerbread-emoji-oboznachenie-klavish-na-klaviature-chto-znachit", "t": "🧁 Gingerbread Emoji на клавиатуре: где найти и как вставить", "i": "🔣", "c": "spetssimvoly-i-znaki"}, {"s": "gibridnaya-klaviatura-chto-eto", "t": "Гибридная клавиатура: что это, виды, плюсы и минусы (2026)", "i": "🔌", "c": "podklyuchenie-i-nastrojka"}, {"s": "gibkaya-klaviatura-chto-eto", "t": "Гибкая клавиатура: что это, виды, особенности работы и как выбрать", "i": "🔌", "c": "podklyuchenie-i-nastrojka"}, {"s": "gibridnye-klaviatury-chto-takoe", "t": "Гибридные клавиатуры: что это такое, виды и особенности выбора", "i": "🔌", "c": "podklyuchenie-i-nastrojka"}, {"s": "gitara-s-klaviaturoj-kak-nazyvaetsya", "t": "Гитара с клавиатурой: как называется, виды и названия моделей", "i": "💻", "c": "virtualnaya-klaviatura"}, {"s": "gigteg-kak-pomenyat-raskladku-klaviatury", "t": "Как поменять раскладку клавиатуры на Gigabyte: полные инструкции и лайфхаки", "i": "🌐", "c": "raskladka-i-yazyki"}, {"s": "gifka-gde-chuvak-betsya-ob-klaviaturu-golovoj", "t": "Гифка где чувак бьется об клавиатуру: смысл и использование", "i": "📁", "c": "drugoe"}]