[{"s": "nier-automata-kak-nastroit-upravlenie-na-klaviature", "t": "Настройка управления в NieR:Automata на клавиатуре — полное руководство", "i": "🎮", "c": "igrovye-nastrojki"}, {"s": "nioh-kak-sdelat-raskladku-dlya-klaviatury", "t": "Как сделать раскладку для клавиатуры в Nioh: полный гайд 2026", "i": "🎮", "c": "igrovye-nastrojki"}, {"s": "nioh-2-kak-parirovat-na-klaviature", "t": "Как парировать в Nioh 2 на клавиатуре: гид 2026", "i": "🎮", "c": "igrovye-nastrojki"}, {"s": "nioh-kak-pomenyat-upravlenie-na-klaviature", "t": "Nioh: как изменить управление на клавиатуре — пошаговая инструкция", "i": "🎮", "c": "igrovye-nastrojki"}, {"s": "nier-automata-kak-igrat-na-klaviature", "t": "NieR:Automata на клавиатуре — полное руководство по управлению", "i": "🎮", "c": "igrovye-nastrojki"}, {"s": "niokh-2-kak-igrat-na-klaviature", "t": "Nioh 2 на клавиатуре: настройка управления и горячие клавиши", "i": "🎮", "c": "igrovye-nastrojki"}, {"s": "nioh-kak-igrat-na-klaviature", "t": "Nioh на клавиатуре: полное руководство по управлению и настройке 2026", "i": "🎮", "c": "igrovye-nastrojki"}, {"s": "nizhnij-i-verkhnij-registr-klaviatury-chto-eto-takoe", "t": "Нижний и верхний регистр на клавиатуре: что это и как переключать", "i": "🌐", "c": "raskladka-i-yazyki"}, {"s": "nioh-2-kak-pomenyat-upravlenie-na-klaviaturu", "t": "Nioh 2: Как настроить управление клавиатурой и мышью на ПК", "i": "🎮", "c": "igrovye-nastrojki"}, {"s": "nizhnij-slesh-na-klaviature-eto-kakie", "t": "Где находится нижний слэш на клавиатуре: расположение и ввод", "i": "🔣", "c": "spetssimvoly-i-znaki"}, {"s": "nioh-2-kak-sdelat-knopki-klaviatury", "t": "Nioh 2: Настройка клавиатуры и мыши, переназначение кнопок на ПК", "i": "🎮", "c": "igrovye-nastrojki"}, {"s": "nioh-kak-na-klaviature", "t": "Nioh на клавиатуре: настройка управления, переназначение и горячие клавиши", "i": "🎮", "c": "igrovye-nastrojki"}, {"s": "nizhnij-ryad-klaviatury-ne-rabotaet-chto-delat", "t": "Нижний ряд клавиатуры не работает: причины и способы ремонта", "i": "🛠️", "c": "remont-i-ustranenie-neispravnostej"}, {"s": "nier-automata-kak-uklonyatsya-na-klaviature", "t": "Nier Automata: Как уклоняться на клавиатуре (PC)", "i": "🎮", "c": "igrovye-nastrojki"}, {"s": "nier-automata-kak-izmenit-uklonenie-na-klaviature", "t": "Как изменить уклонение в Nier Automata на клавиатуре: переназначение кнопок", "i": "🎮", "c": "igrovye-nastrojki"}, {"s": "nizhnij-shtrikh-na-klaviature-sdelat-kak", "t": "Как поставить нижний штрих на клавиатуре: все способы и комбинации", "i": "🔣", "c": "spetssimvoly-i-znaki"}, {"s": "nioh-kak-nastroit-upravlenie-na-klaviature", "t": "Nioh: как настроить управление на клавиатуре — полная инструкция", "i": "🎮", "c": "igrovye-nastrojki"}, {"s": "nioh-kak-pomenyat-upravlenie-s-gejmpada-na-klaviaturu", "t": "Nioh: как поменять управление с геймпада на клавиатуру — Полная инструкция", "i": "🎮", "c": "igrovye-nastrojki"}, {"s": "nidhogg-2-kak-igrat-vdvoem-na-odnoj-klaviature", "t": "Как играть в Nidhogg 2 вдвоем на одной клавиатуре", "i": "🎮", "c": "igrovye-nastrojki"}, {"s": "ninja-blade-kak-povysit-uroven-mecha-na-klaviature", "t": "Ninja Blade: как повысить уровень меча на клавиатуре — полное руководство", "i": "🎮", "c": "igrovye-nastrojki"}, {"s": "nizkoprofilnaya-klaviatura-chto-eto", "t": "Низкопрофильная клавиатура: что это, плюсы и минусы", "i": "📁", "c": "drugoe"}, {"s": "nizhnee-podcherkivanie-na-klaviature-kompyutera-kak-postavit-v-anglijskom-registre", "t": "Как поставить нижнее подчеркивание на клавиатуре: полное руководство", "i": "🔣", "c": "spetssimvoly-i-znaki"}, {"s": "nintendo-switch-emulator-for-pc-kak-poigrat-s-klaviaturoj-i-myshyu", "t": "Как настроить клавиатуру и мышь в эмуляторе Nintendo Switch на ПК", "i": "🎮", "c": "igrovye-nastrojki"}, {"s": "nizhnee-tire-na-klaviature-kak-postavit-v-anglijskom-yazyke", "t": "Как поставить нижнее тире на клавиатуре: английская раскладка и горячие клавиши", "i": "🔣", "c": "spetssimvoly-i-znaki"}, {"s": "nizhnij-registr-na-klaviature-kak-sdelat", "t": "Как сделать нижний регистр: полное руководство по клавиатуре", "i": "⚡", "c": "goryachie-klavishi"}, {"s": "nizhnij-probel-na-klaviature-noutbuka-kak-postavit", "t": "Как поставить нижний пробел на ноутбуке: 5 рабочих способов и настройки", "i": "🔣", "c": "spetssimvoly-i-znaki"}, {"s": "nizhnyaya-cherta-na-klaviature-kak-postavit", "t": "Как поставить нижнюю черту на клавиатуре: все способы для Windows и Mac", "i": "🔣", "c": "spetssimvoly-i-znaki"}, {"s": "nizhnij-registr-na-klaviature-telefona-chto-eto-takoe", "t": "Нижний регистр на клавиатуре телефона: что это и как работает", "i": "💻", "c": "virtualnaya-klaviatura"}, {"s": "nioh-2-kak-postavit-raskladku-klaviatury", "t": "Как исправить раскладку клавиатуры в Nioh 2: полное руководство", "i": "🎮", "c": "igrovye-nastrojki"}, {"s": "nioh-kak-pomenyat-upravlenie-na-klaviaturu", "t": "Как настроить управление клавиатурой в Nioh: полная инструкция по переназначению", "i": "🎮", "c": "igrovye-nastrojki"}, {"s": "nioh-kak-strelyat-iz-luka-na-klaviature", "t": "Nioh: как стрелять из лука на клавиатуре — полное руководство", "i": "🎮", "c": "igrovye-nastrojki"}, {"s": "nioh-kak-sdelat-otobrazhenie-klaviatury-na-kompyutere", "t": "Как включить клавиатуру в Nioh на ПК: настройки и привязка", "i": "🎮", "c": "igrovye-nastrojki"}, {"s": "nioh-2-kak-igrat-na-klaviature", "t": "Nioh 2 на клавиатуре: настройка управления, раскладка и советы", "i": "🎮", "c": "igrovye-nastrojki"}, {"s": "nizhnij-probel-na-klaviature-kak-postavit", "t": "Как поставить нижний пробел на клавиатуре: все способы и решения", "i": "🔣", "c": "spetssimvoly-i-znaki"}, {"s": "nizhnij-registr-na-klaviature-telefona-chto-eto", "t": "Нижний регистр на клавиатуре телефона: что это и как включить", "i": "📱", "c": "klaviatury-na-smartfonakh"}, {"s": "nioh-2-kak-vklyuchit-demona-na-klaviature", "t": "Nioh 2: Как включить демонизацию (дьявольскую трансформацию) на клавиатуре", "i": "🎮", "c": "igrovye-nastrojki"}, {"s": "nizhnee-podcherkivanie-na-klaviature-kompyutera-kak-sdelat", "t": "Как поставить нижнее подчеркивание на клавиатуре: полные инструкции", "i": "🔣", "c": "spetssimvoly-i-znaki"}, {"s": "ninja-gaiden-master-collection-kak-poigrat-na-klaviature", "t": "Как играть в Ninja Gaiden Master Collection на клавиатуре ПК", "i": "🎮", "c": "igrovye-nastrojki"}, {"s": "nizhnij-defis-na-klaviature-kak-postavit", "t": "Как поставить нижний дефис на клавиатуре: быстрые способы и решения", "i": "🔣", "c": "spetssimvoly-i-znaki"}, {"s": "nizhnyaya-chertochka-na-klaviature-kak-sdelat", "t": "Как поставить нижнюю черточку на клавиатуре: способы и решения проблем", "i": "🔣", "c": "spetssimvoly-i-znaki"}, {"s": "nioh-kak-sdelat-otobrazhenie-klaviatury", "t": "Nioh: как включить отображение клавиатуры на экране", "i": "🎮", "c": "igrovye-nastrojki"}, {"s": "ninja-gaiden-sigma-kak-igrat-na-klaviature", "t": "Ninja Gaiden Sigma: Настройка управления на клавиатуре и клавиши", "i": "🎮", "c": "igrovye-nastrojki"}]